{
  "caution": {
    "height": 25,
    "pixelRatio": 1,
    "width": 25,
    "x": 74,
    "y": 0
  },
  "caution_selected": {
    "height": 25,
    "pixelRatio": 1,
    "width": 25,
    "x": 99,
    "y": 0
  },
  "closed": {
    "height": 32,
    "pixelRatio": 1,
    "width": 32,
    "x": 0,
    "y": 37
  },
  "closed_selected": {
    "height": 32,
    "pixelRatio": 1,
    "width": 32,
    "x": 32,
    "y": 37
  },
  "longterm": {
    "height": 32,
    "pixelRatio": 1,
    "width": 32,
    "x": 64,
    "y": 37
  },
  "longterm_selected": {
    "height": 32,
    "pixelRatio": 1,
    "width": 32,
    "x": 96,
    "y": 37
  },
  "open": {
    "height": 37,
    "pixelRatio": 1,
    "width": 37,
    "x": 0,
    "y": 0
  },
  "open_selected": {
    "height": 37,
    "pixelRatio": 1,
    "width": 37,
    "x": 37,
    "y": 0
  }
}